message_bus/__init__.py
message_bus/abc.py
message_bus/bus.py
message_bus-0.0.1a0.data/data/README.md/README.md
message_bus-0.0.1a0.dist-info/LICENSE
message_bus-0.0.1a0.dist-info/METADATA
message_bus-0.0.1a0.dist-info/WHEEL
message_bus-0.0.1a0.dist-info/top_level.txt
message_bus-0.0.1a0.dist-info/RECORD
